qmpy/__init__.py
qmpy/models.py
qmpy/__pycache__/__init__.cpython-35.pyc
qmpy/__pycache__/__init__.cpython-36.pyc
qmpy/__pycache__/__init__.cpython-37.pyc
qmpy/analysis/__init__.py
qmpy/analysis/bond_valence.py
qmpy/analysis/database.py
qmpy/analysis/elastic.py
qmpy/analysis/griddata.py
qmpy/analysis/interface_finder.py
qmpy/analysis/miedema.py
qmpy/analysis/mining.py
qmpy/analysis/nearest_neighbors.py
qmpy/analysis/network.py
qmpy/analysis/nn.pyx
qmpy/analysis/pdf.py
qmpy/analysis/tests.py
qmpy/analysis/xrd.py
qmpy/analysis/__pycache__/__init__.cpython-35.pyc
qmpy/analysis/__pycache__/__init__.cpython-36.pyc
qmpy/analysis/__pycache__/__init__.cpython-37.pyc
qmpy/analysis/debye/debye_model.py
qmpy/analysis/debye/quasi_harmonic.py
qmpy/analysis/debye/read_file.py
qmpy/analysis/debye/sound_waves.py
qmpy/analysis/debye/exp_PbS/PbS_answers
qmpy/analysis/debye/exp_PbS/PbS_debye
qmpy/analysis/debye/exp_PbS/PbS_density
qmpy/analysis/debye/exp_PbS/PbS_exp_C
qmpy/analysis/debye/exp_PbTe/PbTe_density
qmpy/analysis/debye/exp_PbTe/PbTe_exp_C
qmpy/analysis/debye/exp_PbTe/PbTe_model_VII_C
qmpy/analysis/debye/lead/Pb_answers
qmpy/analysis/debye/lead/Pb_debey_temp
qmpy/analysis/debye/lead/Pb_density
qmpy/analysis/debye/lead/Pb_exp_C
qmpy/analysis/debye/wolfram_tungsten/W_density
qmpy/analysis/debye/wolfram_tungsten/W_exp_C
qmpy/analysis/symmetry/__init__.py
qmpy/analysis/symmetry/routines.py
qmpy/analysis/symmetry/spacegroup.py
qmpy/analysis/symmetry/tests.py
qmpy/analysis/symmetry/__pycache__/__init__.cpython-35.pyc
qmpy/analysis/symmetry/__pycache__/__init__.cpython-36.pyc
qmpy/analysis/symmetry/__pycache__/routines.cpython-35.pyc
qmpy/analysis/symmetry/__pycache__/routines.cpython-36.pyc
qmpy/analysis/symmetry/__pycache__/spacegroup.cpython-35.pyc
qmpy/analysis/symmetry/__pycache__/spacegroup.cpython-36.pyc
qmpy/analysis/test/bond_valence_test.py
qmpy/analysis/test/dists.txt
qmpy/analysis/test/ising_test.py
qmpy/analysis/test/nn_test.py
qmpy/analysis/test/pdf_test.py
qmpy_tri-2022.7.21.dist-info/LICENSE.txt
qmpy_tri-2022.7.21.dist-info/METADATA
qmpy_tri-2022.7.21.dist-info/WHEEL
qmpy_tri-2022.7.21.dist-info/top_level.txt
qmpy_tri-2022.7.21.dist-info/RECORD
